{
  "project_info": {
    "project_number": "1088154574515",
    "project_id": "the-dharmarth",
    "storage_bucket": "the-dharmarth.firebasestorage.app"
  },
  "client": [
    {
      "client_info": {
        "mobilesdk_app_id": "1:1088154574515:android:f21459c3f314e045cc5ac6",
        "android_client_info": {
          "package_name": "com.thedharmarth.foundation"
        }
      },
      "oauth_client": [],
      "api_key": [
        {
          "current_key": "AIzaSyB3G1m1xHFEh33_nYQFvjVQ5tT6i0McFCE"
        }
      ],
      "services": {
        "appinvite_service": {
          "other_platform_oauth_client": []
        }
      }
    }
  ],
  "configuration_version": "1"
}